wd/di/__init__.py
wd/di/config.py
wd/di/container.py
wd/di/descriptors.py
wd/di/exceptions.py
wd/di/lifetimes.py
wd/di/middleware.py
wd/di/middleware_di.py
wd/di/service_collection.py
wd_di-0.2.14.dist-info/METADATA
wd_di-0.2.14.dist-info/WHEEL
wd_di-0.2.14.dist-info/licenses/LICENSE
wd_di-0.2.14.dist-info/RECORD
