Metadata-Version: 2.4
Name: wd-di
Version: 0.2.14
Summary: .NET Core Dependency Injection for Python
Project-URL: Homepage, https://github.com/whiteducksoftware/wd-di
Project-URL: Documentation, https://whiteducksoftware.github.io/wd-di/
Project-URL: Repository, https://github.com/whiteducksoftware/wd-di
Project-URL: Bug Tracker, https://github.com/whiteducksoftware/wd-di/issues
Author-email: Andre Ratzenberger <andre.ratzenberger@whiteduck.de>
License: MIT
License-File: LICENSE
Classifier: License :: OSI Approved :: MIT License
Classifier: Operating System :: OS Independent
Classifier: Programming Language :: Python :: 3
Requires-Python: >=3.10
